aoc/__init__.py
aoc/tasks/__init__.py
aoc/tasks/aoc.py
aoc/utils/__init__.py
aoc/utils/parsing.py
aoc/utils/setup.py
task_jogger_aoc-0.1.1.dist-info/LICENSE
task_jogger_aoc-0.1.1.dist-info/METADATA
task_jogger_aoc-0.1.1.dist-info/WHEEL
task_jogger_aoc-0.1.1.dist-info/top_level.txt
task_jogger_aoc-0.1.1.dist-info/RECORD
