Metadata-Version: 2.1
Name: task-jogger-aoc
Version: 0.1.1
Summary: A structural template and runner for Advent of Code solutions written in Python.
Home-page: https://github.com/oogles/task-jogger-aoc
Author: Alex Church
Author-email: alex@church.id.au
License: MIT
Project-URL: Bug Tracker, https://github.com/oogles/task-jogger-aoc/issues
Classifier: Intended Audience :: Developers
Classifier: License :: OSI Approved :: MIT License
Classifier: Operating System :: OS Independent
Classifier: Programming Language :: Python :: 3
Requires-Python: >=3.8
License-File: LICENSE
Requires-Dist: task-jogger >=1.1.1
